webrobot/__init__.py
webrobot/element.py
webrobot/webdriver.py
webrobot/SeleniumWheel/__init__.py
webrobot/SeleniumWheel/android/__init__.py
webrobot/SeleniumWheel/android/webdriver.py
webrobot/SeleniumWheel/blackberry/__init__.py
webrobot/SeleniumWheel/blackberry/webdriver.py
webrobot/SeleniumWheel/chrome/__init__.py
webrobot/SeleniumWheel/chrome/options.py
webrobot/SeleniumWheel/chrome/remote_connection.py
webrobot/SeleniumWheel/chrome/service.py
webrobot/SeleniumWheel/chrome/webdriver.py
webrobot/SeleniumWheel/common/__init__.py
webrobot/SeleniumWheel/common/action_chains.py
webrobot/SeleniumWheel/common/alert.py
webrobot/SeleniumWheel/common/by.py
webrobot/SeleniumWheel/common/desired_capabilities.py
webrobot/SeleniumWheel/common/keys.py
webrobot/SeleniumWheel/common/proxy.py
webrobot/SeleniumWheel/common/service.py
webrobot/SeleniumWheel/common/touch_actions.py
webrobot/SeleniumWheel/common/utils.py
webrobot/SeleniumWheel/common/actions/__init__.py
webrobot/SeleniumWheel/common/actions/action_builder.py
webrobot/SeleniumWheel/common/actions/input_device.py
webrobot/SeleniumWheel/common/actions/interaction.py
webrobot/SeleniumWheel/common/actions/key_actions.py
webrobot/SeleniumWheel/common/actions/key_input.py
webrobot/SeleniumWheel/common/actions/mouse_button.py
webrobot/SeleniumWheel/common/actions/pointer_actions.py
webrobot/SeleniumWheel/common/actions/pointer_input.py
webrobot/SeleniumWheel/common/html5/__init__.py
webrobot/SeleniumWheel/common/html5/application_cache.py
webrobot/SeleniumWheel/edge/__init__.py
webrobot/SeleniumWheel/edge/options.py
webrobot/SeleniumWheel/edge/service.py
webrobot/SeleniumWheel/edge/webdriver.py
webrobot/SeleniumWheel/firefox/__init__.py
webrobot/SeleniumWheel/firefox/extension_connection.py
webrobot/SeleniumWheel/firefox/firefox_binary.py
webrobot/SeleniumWheel/firefox/firefox_profile.py
webrobot/SeleniumWheel/firefox/options.py
webrobot/SeleniumWheel/firefox/remote_connection.py
webrobot/SeleniumWheel/firefox/service.py
webrobot-1.5.0.dist-info/LICENSE
webrobot-1.5.0.dist-info/METADATA
webrobot-1.5.0.dist-info/WHEEL
webrobot-1.5.0.dist-info/top_level.txt
webrobot-1.5.0.dist-info/RECORD
