Metadata-Version: 2.1
Name: webrobot
Version: 1.5.0
Summary: This is a Selenium based Web automation wheel that is more user-friendly than Selenium!
Home-page: https://github.com/deitimicro/wheels
Author: Deity Micro
Author-email: deitimicro@gmail.com
License: UNKNOWN
Platform: UNKNOWN
Classifier: Programming Language :: Python :: 3
Classifier: License :: OSI Approved :: MIT License
Classifier: Operating System :: OS Independent
Requires-Python: >=3.6
Requires-Dist: selenium
